[
  {
    "key": "ap4_2_1_1",
    "wrappers": [
      "title-div"
    ],
    "templateOptions": {
      "label": "4.2.1.1 University Laboratory"
    },
    "fieldGroup": [
      {
        "template": "<p>Next, specify in which location of the University the tasks with agents, biological material, genetically modified organisms, hazardous chemicals, radioactive substances and/or nanoparticles will be carried out.</p>"
      },
      {
        "wrappers": [
          "info-div"
        ],
        "template": "You do not need to fill out the asset code if you have indicated a laboratory of the services and sections of the Scientific and Technical Research Area (ACTI).</p>"
      },
      {
        "type": "table-crud",
        "key": "laboratorioLocalTable",
        "templateOptions": {
          "entity": "local",
          "gender": "male"
        },
        "fieldArray": {
          "templateOptions": {
            "text": "Local"
          },
          "fieldGroup": [
            {
              "key": "codPatrimonial",
              "type": "input",
              "templateOptions": {
                "label": "Asset Code",
                "order": 10
              }
            },
            {
              "key": "nivelContencion",
              "type": "select",
              "templateOptions": {
                "label": "Containment level",
                "order": 20,
                "options": [
                  {
                    "value": "1",
                    "label": "C1"
                  },
                  {
                    "value": "2",
                    "label": "C2"
                  },
                  {
                    "value": "3",
                    "label": "C3"
                  },
                  {
                    "value": "4",
                    "label": "C4"
                  }
                ]
              }
            },
            {
              "key": "ubicacion",
              "type": "input",
              "templateOptions": {
                "label": "Location",
                "order": 30
              }
            },
            {
              "key": "certificadoIdoneidad",
              "type": "select",
              "templateOptions": {
                "label": "Certificate of suitability",
                "order": 40,
                "options": [
                  {
                    "value": "1",
                    "label": "Yes"
                  },
                  {
                    "value": "2",
                    "label": "No"
                  }
                ]
              }
            },
            {
              "key": "numeroRegistroServicioPrevencion",
              "type": "input",
              "templateOptions": {
                "label": "Reg. No. Prevention Service",
                "order": 50
              }
            },
            {
              "key": "fecha",
              "type": "datepicker",
              "templateOptions": {
                "label": "Date",
                "luxonFormat": "shortDate",
                "order": 60
              }
            }
          ]
        }
      }
    ]
  }
]