<?xml version="1.1" encoding="UTF-8" standalone="no"?>
<databaseChangeLog xmlns="http://www.liquibase.org/xml/ns/dbchangelog" xmlns:ext="http://www.liquibase.org/xml/ns/dbchangelog-ext" xmlns:pro="http://www.liquibase.org/xml/ns/pro" xmlns:xsi="http://www.w3.org/2001/XMLSchema-instance" xsi:schemaLocation="http://www.liquibase.org/xml/ns/dbchangelog-ext http://www.liquibase.org/xml/ns/dbchangelog/dbchangelog-ext.xsd http://www.liquibase.org/xml/ns/pro http://www.liquibase.org/xml/ns/pro/liquibase-pro-3.8.xsd http://www.liquibase.org/xml/ns/dbchangelog http://www.liquibase.org/xml/ns/dbchangelog/dbchangelog-3.8.xsd">
  <property name="schemaPrefix" value="" />

  <changeSet context="!test" author="master" id="0000000000011-solicitud_modalidad">
    <sql>
      UPDATE ${schemaPrefix}solicitud_modalidad sm SET programa_convocatoria_id=(
        SELECT
          max(cec.programa_id)
        FROM ${schemaPrefix}convocatoria_entidad_convocante cec 
        WHERE 
          cec.convocatoria_id=(
            SELECT
              s.convocatoria_id
            FROM ${schemaPrefix}solicitud s
            WHERE s.id = sm.solicitud_id
          )
          AND  sm.entidad_ref=cec.entidad_ref
      )
    </sql>
  </changeSet>
  <changeSet context="!test" author="master" id="0000000000011-proyecto_entidad_convocante">
    <sql>
      UPDATE ${schemaPrefix}proyecto_entidad_convocante pec SET programa_id=(
        SELECT
          sm.programa_id
        FROM ${schemaPrefix}solicitud_modalidad sm 
        WHERE 
          sm.solicitud_id=(
            SELECT
              p.solicitud_id
            FROM ${schemaPrefix}proyecto p
            WHERE p.id = pec.proyecto_id
          )
          AND sm.entidad_ref=pec.entidad_ref
          AND sm.programa_convocatoria_id=pec.programa_convocatoria_id
      ) 
      WHERE 
        pec.programa_id IS NULL
        AND pec.programa_convocatoria_id IS NOT NULL
    </sql>
  </changeSet>

</databaseChangeLog>